gittr/__init__.py
gittr/cli/__init__.py
gittr/cli/__main__.py
gittr/cli/_version.py
gittr/cli/action.py
gittr/cli/cli.py
gittr/cli/utils.py
ght-0.1.2.dist-info/LICENSE
ght-0.1.2.dist-info/METADATA
ght-0.1.2.dist-info/WHEEL
ght-0.1.2.dist-info/entry_points.txt
ght-0.1.2.dist-info/top_level.txt
ght-0.1.2.dist-info/RECORD
