Metadata-Version: 2.1
Name: ght
Version: 0.1.2
Summary: GIT Template Render (GITTR)
Home-page: https://github.com/zeroae/ght
Author: Patrick Sodré
Author-email: psodre@gmail.com
License: BSD
Keywords: cli gittr cookiecutter template
Platform: UNKNOWN
Classifier: Development Status :: 2 - Pre-Alpha
Classifier: Intended Audience :: Developers
Classifier: License :: OSI Approved :: BSD License
Classifier: Natural Language :: English
Classifier: Programming Language :: Python :: 3
Classifier: Programming Language :: Python :: 3.6
Classifier: Programming Language :: Python :: 3.7
Classifier: Programming Language :: Python :: 3.8
Requires-Python: >=3.8
Requires-Dist: click (>=7.0)
Requires-Dist: click-plugins
Requires-Dist: entrypoints
Requires-Dist: gitpython (<3.2,>=3.1.0)
Requires-Dist: jinja2 (<3,>=2.11.1)
Requires-Dist: jinja2-time (==0.2.0)
Requires-Dist: pyyaml (<6,>=5.3.1)
Provides-Extra: doc
Requires-Dist: sphinx ; extra == 'doc'
Requires-Dist: sphinx-autoapi ; extra == 'doc'
Requires-Dist: sphinx-click ; extra == 'doc'
Requires-Dist: watchdog ; extra == 'doc'
Provides-Extra: test
Requires-Dist: pytest (>=3) ; extra == 'test'
Requires-Dist: pytest-cov ; extra == 'test'
